Workbook

Sheet Start Here
B2: Income & Expense Tracker — 2026
B3: Set up your two income sources and your expense categories below, then log every transaction on the Income and Expenses tabs. All summaries update automatically.
B5: 1. YOUR INCOME SOURCES
B6: Source 1 | C6: Salary | D6: Rename this to your main income source (e.g. your job).
B7: Source 2 | C7: Freelance | D7: Rename this to your second income source (e.g. side business, rental).
B9: 2. YOUR EXPENSE CATEGORIES
C10: Rent / Mortgage | D10: Edit any of these labels to suit you — the summaries follow whatever you type here.
C11: Utilities
C12: Groceries
C13: Transport
C14: Insurance
C15: Health & Medical
C16: Dining Out
C17: Shopping
C18: Subscriptions
C19: Entertainment
C20: Travel
C21: Debt Payments
C22: Savings / Investments
C23: Other
B25: 3. HOW TO USE IT
B26: Yellow cells | C26: The only cells you edit on this tab — source names and categories.
B27: Income tab | C27: One row per payment received: date, which source, amount.
B28: Expenses tab | C28: One row per thing you spend: date, category, amount.
B29: Weekly Summary | C29: Every week of the year, Monday to Sunday. Fills in by itself.
B30: Monthly Summary | C30: Month-by-month totals plus a spend-by-category grid.
B31: Example rows | C31: Each log tab has one grey example row — delete it once you start.
B32: Everything else | C32: Calculated. Don't type over a formula or that row stops updating.
B34: Assumptions: weeks run Monday–Sunday; the calendar covers 2026 (week 1 starts 29-Dec-2025); amounts are entered as positive numbers on both tabs; currency symbol is $ — change the cell format if you use another.

Sheet Income
A1: Income Log
A2: Log every payment you receive. Pick the source from the dropdown.
A4: Date | B4: Source | C4: Description | D4: Amount
A5: 46235 | B5: Salary | C5: EXAMPLE — delete this row | D5: 3200
C156: TOTAL LOGGED | D156: =SUM(D5:D154)

Sheet Expenses
A1: Expense Log
A2: Log every thing you spend. Pick the category from the dropdown.
A4: Date | B4: Category | C4: Description | D4: Amount | E4: Paid With
A5: 46237 | B5: Groceries | C5: EXAMPLE — delete this row | D5: 84.5 | E5: Debit card
C306: TOTAL LOGGED | D306: =SUM(D5:D304)

Sheet Weekly Summary
A1: Weekly Summary — 2026
A2: Weeks run Monday to Sunday. Every figure here is calculated from the Income and Expenses tabs.
A4: Week | B4: Week Starting | C4: Week Ending | D4: =CONCATENATE("Income — ",'Start Here'!$C$6) | E4: =CONCATENATE("Income — ",'Start Here'!$C$7) | F4: Total Income | G4: Total Expenses | H4: Net (Saved) | I4: Savings Rate
A5: 1 | B5: 46020 | C5: =B5+6 | D5: =SUMIFS(Income!$D$5:$D$154,Income!$A$5:$A$154,">="&$B5,Income!$A$5:$A$154,"<="&$C5,Income!$B$5:$B$154,'Start Here'!$C$6) | E5: =SUMIFS(Income!$D$5:$D$154,Income!$A$5:$A$154,">="&$B5,Income!$A$5:$A$154,"<="&$C5,Income!$B$5:$B$154,'Start Here'!$C$7) | F5: =D5+E5 | G5: =SUMIFS(Expenses!$D$5:$D$304,Expenses!$A$5:$A$304,">="&$B5,Expenses!$A$5:$A$304,"<="&$C5) | H5: =F5-G5 | I5: =IFERROR(H5/F5,"")
A6: 2 | B6: 46027 | C6: =B6+6 | D6: =SUMIFS(Income!$D$5:$D$154,Income!$A$5:$A$154,">="&$B6,Income!$A$5:$A$154,"<="&$C6,Income!$B$5:$B$154,'Start Here'!$C$6) | E6: =SUMIFS(Income!$D$5:$D$154,Income!$A$5:$A$154,">="&$B6,Income!$A$5:$A$154,"<="&$C6,Income!$B$5:$B$154,'Start Here'!$C$7) | F6: =D6+E6 | G6: =SUMIFS(Expenses!$D$5:$D$304,Expenses!$A$5:$A$304,">="&$B6,Expenses!$A$5:$A$304,"<="&$C6) | H6: =F6-G6 | I6: =IFERROR(H6/F6,"")
A7: 3 | B7: 46034 | C7: =B7+6 | D7: =SUMIFS(Income!$D$5:$D$154,Income!$A$5:$A$154,">="&$B7,Income!$A$5:$A$154,"<="&$C7,Income!$B$5:$B$154,'Start Here'!$C$6) | E7: =SUMIFS(Income!$D$5:$D$154,Income!$A$5:$A$154,">="&$B7,Income!$A$5:$A$154,"<="&$C7,Income!$B$5:$B$154,'Start Here'!$C$7) | F7: =D7+E7 | G7: =SUMIFS(Expenses!$D$5:$D$304,Expenses!$A$5:$A$304,">="&$B7,Expenses!$A$5:$A$304,"<="&$C7) | H7: =F7-G7 | I7: =IFERROR(H7/F7,"")
A8: 4 | B8: 46041 | C8: =B8+6 | D8: =SUMIFS(Income!$D$5:$D$154,Income!$A$5:$A$154,">="&$B8,Income!$A$5:$A$154,"<="&$C8,Income!$B$5:$B$154,'Start Here'!$C$6) | E8: =SUMIFS(Income!$D$5:$D$154,Income!$A$5:$A$154,">="&$B8,Income!$A$5:$A$154,"<="&$C8,Income!$B$5:$B$154,'Start Here'!$C$7) | F8: =D8+E8 | G8: =SUMIFS(Expenses!$D$5:$D$304,Expenses!$A$5:$A$304,">="&$B8,Expenses!$A$5:$A$304,"<="&$C8) | H8: =F8-G8 | I8: =IFERROR(H8/F8,"")
A9: 5 | B9: 46048 | C9: =B9+6 | D9: =SUMIFS(Income!$D$5:$D$154,Income!$A$5:$A$154,">="&$B9,Income!$A$5:$A$154,"<="&$C9,Income!$B$5:$B$154,'Start Here'!$C$6) | E9: =SUMIFS(Income!$D$5:$D$154,Income!$A$5:$A$154,">="&$B9,Income!$A$5:$A$154,"<="&$C9,Income!$B$5:$B$154,'Start Here'!$C$7) | F9: =D9+E9 | G9: =SUMIFS(Expenses!$D$5:$D$304,Expenses!$A$5:$A$304,">="&$B9,Expenses!$A$5:$A$304,"<="&$C9) | H9: =F9-G9 | I9: =IFERROR(H9/F9,"")
A10: 6 | B10: 46055 | C10: =B10+6 | D10: =SUMIFS(Income!$D$5:$D$154,Income!$A$5:$A$154,">="&$B10,Income!$A$5:$A$154,"<="&$C10,Income!$B$5:$B$154,'Start Here'!$C$6) | E10: =SUMIFS(Income!$D$5:$D$154,Income!$A$5:$A$154,">="&$B10,Income!$A$5:$A$154,"<="&$C10,Income!$B$5:$B$154,'Start Here'!$C$7) | F10: =D10+E10 | G10: =SUMIFS(Expenses!$D$5:$D$304,Expenses!$A$5:$A$304,">="&$B10,Expenses!$A$5:$A$304,"<="&$C10) | H10: =F10-G10 | I10: =IFERROR(H10/F10,"")
A11: 7 | B11: 46062 | C11: =B11+6 | D11: =SUMIFS(Income!$D$5:$D$154,Income!$A$5:$A$154,">="&$B11,Income!$A$5:$A$154,"<="&$C11,Income!$B$5:$B$154,'Start Here'!$C$6) | E11: =SUMIFS(Income!$D$5:$D$154,Income!$A$5:$A$154,">="&$B11,Income!$A$5:$A$154,"<="&$C11,Income!$B$5:$B$154,'Start Here'!$C$7) | F11: =D11+E11 | G11: =SUMIFS(Expenses!$D$5:$D$304,Expenses!$A$5:$A$304,">="&$B11,Expenses!$A$5:$A$304,"<="&$C11) | H11: =F11-G11 | I11: =IFERROR(H11/F11,"")
A12: 8 | B12: 46069 | C12: =B12+6 | D12: =SUMIFS(Income!$D$5:$D$154,Income!$A$5:$A$154,">="&$B12,Income!$A$5:$A$154,"<="&$C12,Income!$B$5:$B$154,'Start Here'!$C$6) | E12: =SUMIFS(Income!$D$5:$D$154,Income!$A$5:$A$154,">="&$B12,Income!$A$5:$A$154,"<="&$C12,Income!$B$5:$B$154,'Start Here'!$C$7) | F12: =D12+E12 | G12: =SUMIFS(Expenses!$D$5:$D$304,Expenses!$A$5:$A$304,">="&$B12,Expenses!$A$5:$A$304,"<="&$C12) | H12: =F12-G12 | I12: =IFERROR(H12/F12,"")
A13: 9 | B13: 46076 | C13: =B13+6 | D13: =SUMIFS(Income!$D$5:$D$154,Income!$A$5:$A$154,">="&$B13,Income!$A$5:$A$154,"<="&$C13,Income!$B$5:$B$154,'Start Here'!$C$6) | E13: =SUMIFS(Income!$D$5:$D$154,Income!$A$5:$A$154,">="&$B13,Income!$A$5:$A$154,"<="&$C13,Income!$B$5:$B$154,'Start Here'!$C$7) | F13: =D13+E13 | G13: =SUMIFS(Expenses!$D$5:$D$304,Expenses!$A$5:$A$304,">="&$B13,Expenses!$A$5:$A$304,"<="&$C13) | H13: =F13-G13 | I13: =IFERROR(H13/F13,"")
A14: 10 | B14: 46083 | C14: =B14+6 | D14: =SUMIFS(Income!$D$5:$D$154,Income!$A$5:$A$154,">="&$B14,Income!$A$5:$A$154,"<="&$C14,Income!$B$5:$B$154,'Start Here'!$C$6) | E14: =SUMIFS(Income!$D$5:$D$154,Income!$A$5:$A$154,">="&$B14,Income!$A$5:$A$154,"<="&$C14,Income!$B$5:$B$154,'Start Here'!$C$7) | F14: =D14+E14 | G14: =SUMIFS(Expenses!$D$5:$D$304,Expenses!$A$5:$A$304,">="&$B14,Expenses!$A$5:$A$304,"<="&$C14) | H14: =F14-G14 | I14: =IFERROR(H14/F14,"")
A15: 11 | B15: 46090 | C15: =B15+6 | D15: =SUMIFS(Income!$D$5:$D$154,Income!$A$5:$A$154,">="&$B15,Income!$A$5:$A$154,"<="&$C15,Income!$B$5:$B$154,'Start Here'!$C$6) | E15: =SUMIFS(Income!$D$5:$D$154,Income!$A$5:$A$154,">="&$B15,Income!$A$5:$A$154,"<="&$C15,Income!$B$5:$B$154,'Start Here'!$C$7) | F15: =D15+E15 | G15: =SUMIFS(Expenses!$D$5:$D$304,Expenses!$A$5:$A$304,">="&$B15,Expenses!$A$5:$A$304,"<="&$C15) | H15: =F15-G15 | I15: =IFERROR(H15/F15,"")
A16: 12 | B16: 46097 | C16: =B16+6 | D16: =SUMIFS(Income!$D$5:$D$154,Income!$A$5:$A$154,">="&$B16,Income!$A$5:$A$154,"<="&$C16,Income!$B$5:$B$154,'Start Here'!$C$6) | E16: =SUMIFS(Income!$D$5:$D$154,Income!$A$5:$A$154,">="&$B16,Income!$A$5:$A$154,"<="&$C16,Income!$B$5:$B$154,'Start Here'!$C$7) | F16: =D16+E16 | G16: =SUMIFS(Expenses!$D$5:$D$304,Expenses!$A$5:$A$304,">="&$B16,Expenses!$A$5:$A$304,"<="&$C16) | H16: =F16-G16 | I16: =IFERROR(H16/F16,"")
... A57: 53 | B57: 46384 | C57: =B57+6 | D57: =SUMIFS(Income!$D$5:$D$154,Income!$A$5:$A$154,">="&$B57,Income!$A$5:$A$154,"<="&$C57,Income!$B$5:$B$154,'Start Here'!$C$6) | E57: =SUMIFS(Income!$D$5:$D$154,Income!$A$5:$A$154,">="&$B57,Income!$A$5:$A$154,"<="&$C57,Income!$B$5:$B$154,'Start Here'!$C$7) | F57: =D57+E57 | G57: =SUMIFS(Expenses!$D$5:$D$304,Expenses!$A$5:$A$304,">="&$B57,Expenses!$A$5:$A$304,"<="&$C57) | H57: =F57-G57 | I57: =IFERROR(H57/F57,"")
A58: YEAR | D58: =SUM(D5:D57) | E58: =SUM(E5:E57) | F58: =SUM(F5:F57) | G58: =SUM(G5:G57) | H58: =F58-G58 | I58: =IFERROR(H58/F58,"")

Sheet Monthly Summary
A1: Monthly Summary — 2026
A2: Totals by month, then a breakdown of where the money went.
A4: Month | B4: Month Start | C4: Month End | D4: =CONCATENATE("Income — ",'Start Here'!$C$6) | E4: =CONCATENATE("Income — ",'Start Here'!$C$7) | F4: Total Income | G4: Total Expenses | H4: Net (Saved) | I4: Savings Rate
A5: 46023 | B5: 46023 | C5: =EOMONTH(B5,0) | D5: =SUMIFS(Income!$D$5:$D$154,Income!$A$5:$A$154,">="&$B5,Income!$A$5:$A$154,"<="&$C5,Income!$B$5:$B$154,'Start Here'!$C$6) | E5: =SUMIFS(Income!$D$5:$D$154,Income!$A$5:$A$154,">="&$B5,Income!$A$5:$A$154,"<="&$C5,Income!$B$5:$B$154,'Start Here'!$C$7) | F5: =D5+E5 | G5: =SUMIFS(Expenses!$D$5:$D$304,Expenses!$A$5:$A$304,">="&$B5,Expenses!$A$5:$A$304,"<="&$C5) | H5: =F5-G5 | I5: =IFERROR(H5/F5,"")
A6: 46054 | B6: 46054 | C6: =EOMONTH(B6,0) | D6: =SUMIFS(Income!$D$5:$D$154,Income!$A$5:$A$154,">="&$B6,Income!$A$5:$A$154,"<="&$C6,Income!$B$5:$B$154,'Start Here'!$C$6) | E6: =SUMIFS(Income!$D$5:$D$154,Income!$A$5:$A$154,">="&$B6,Income!$A$5:$A$154,"<="&$C6,Income!$B$5:$B$154,'Start Here'!$C$7) | F6: =D6+E6 | G6: =SUMIFS(Expenses!$D$5:$D$304,Expenses!$A$5:$A$304,">="&$B6,Expenses!$A$5:$A$304,"<="&$C6) | H6: =F6-G6 | I6: =IFERROR(H6/F6,"")
A7: 46082 | B7: 46082 | C7: =EOMONTH(B7,0) | D7: =SUMIFS(Income!$D$5:$D$154,Income!$A$5:$A$154,">="&$B7,Income!$A$5:$A$154,"<="&$C7,Income!$B$5:$B$154,'Start Here'!$C$6) | E7: =SUMIFS(Income!$D$5:$D$154,Income!$A$5:$A$154,">="&$B7,Income!$A$5:$A$154,"<="&$C7,Income!$B$5:$B$154,'Start Here'!$C$7) | F7: =D7+E7 | G7: =SUMIFS(Expenses!$D$5:$D$304,Expenses!$A$5:$A$304,">="&$B7,Expenses!$A$5:$A$304,"<="&$C7) | H7: =F7-G7 | I7: =IFERROR(H7/F7,"")
A8: 46113 | B8: 46113 | C8: =EOMONTH(B8,0) | D8: =SUMIFS(Income!$D$5:$D$154,Income!$A$5:$A$154,">="&$B8,Income!$A$5:$A$154,"<="&$C8,Income!$B$5:$B$154,'Start Here'!$C$6) | E8: =SUMIFS(Income!$D$5:$D$154,Income!$A$5:$A$154,">="&$B8,Income!$A$5:$A$154,"<="&$C8,Income!$B$5:$B$154,'Start Here'!$C$7) | F8: =D8+E8 | G8: =SUMIFS(Expenses!$D$5:$D$304,Expenses!$A$5:$A$304,">="&$B8,Expenses!$A$5:$A$304,"<="&$C8) | H8: =F8-G8 | I8: =IFERROR(H8/F8,"")
A9: 46143 | B9: 46143 | C9: =EOMONTH(B9,0) | D9: =SUMIFS(Income!$D$5:$D$154,Income!$A$5:$A$154,">="&$B9,Income!$A$5:$A$154,"<="&$C9,Income!$B$5:$B$154,'Start Here'!$C$6) | E9: =SUMIFS(Income!$D$5:$D$154,Income!$A$5:$A$154,">="&$B9,Income!$A$5:$A$154,"<="&$C9,Income!$B$5:$B$154,'Start Here'!$C$7) | F9: =D9+E9 | G9: =SUMIFS(Expenses!$D$5:$D$304,Expenses!$A$5:$A$304,">="&$B9,Expenses!$A$5:$A$304,"<="&$C9) | H9: =F9-G9 | I9: =IFERROR(H9/F9,"")
A10: 46174 | B10: 46174 | C10: =EOMONTH(B10,0) | D10: =SUMIFS(Income!$D$5:$D$154,Income!$A$5:$A$154,">="&$B10,Income!$A$5:$A$154,"<="&$C10,Income!$B$5:$B$154,'Start Here'!$C$6) | E10: =SUMIFS(Income!$D$5:$D$154,Income!$A$5:$A$154,">="&$B10,Income!$A$5:$A$154,"<="&$C10,Income!$B$5:$B$154,'Start Here'!$C$7) | F10: =D10+E10 | G10: =SUMIFS(Expenses!$D$5:$D$304,Expenses!$A$5:$A$304,">="&$B10,Expenses!$A$5:$A$304,"<="&$C10) | H10: =F10-G10 | I10: =IFERROR(H10/F10,"")
A11: 46204 | B11: 46204 | C11: =EOMONTH(B11,0) | D11: =SUMIFS(Income!$D$5:$D$154,Income!$A$5:$A$154,">="&$B11,Income!$A$5:$A$154,"<="&$C11,Income!$B$5:$B$154,'Start Here'!$C$6) | E11: =SUMIFS(Income!$D$5:$D$154,Income!$A$5:$A$154,">="&$B11,Income!$A$5:$A$154,"<="&$C11,Income!$B$5:$B$154,'Start Here'!$C$7) | F11: =D11+E11 | G11: =SUMIFS(Expenses!$D$5:$D$304,Expenses!$A$5:$A$304,">="&$B11,Expenses!$A$5:$A$304,"<="&$C11) | H11: =F11-G11 | I11: =IFERROR(H11/F11,"")
A12: 46235 | B12: 46235 | C12: =EOMONTH(B12,0) | D12: =SUMIFS(Income!$D$5:$D$154,Income!$A$5:$A$154,">="&$B12,Income!$A$5:$A$154,"<="&$C12,Income!$B$5:$B$154,'Start Here'!$C$6) | E12: =SUMIFS(Income!$D$5:$D$154,Income!$A$5:$A$154,">="&$B12,Income!$A$5:$A$154,"<="&$C12,Income!$B$5:$B$154,'Start Here'!$C$7) | F12: =D12+E12 | G12: =SUMIFS(Expenses!$D$5:$D$304,Expenses!$A$5:$A$304,">="&$B12,Expenses!$A$5:$A$304,"<="&$C12) | H12: =F12-G12 | I12: =IFERROR(H12/F12,"")
A13: 46266 | B13: 46266 | C13: =EOMONTH(B13,0) | D13: =SUMIFS(Income!$D$5:$D$154,Income!$A$5:$A$154,">="&$B13,Income!$A$5:$A$154,"<="&$C13,Income!$B$5:$B$154,'Start Here'!$C$6) | E13: =SUMIFS(Income!$D$5:$D$154,Income!$A$5:$A$154,">="&$B13,Income!$A$5:$A$154,"<="&$C13,Income!$B$5:$B$154,'Start Here'!$C$7) | F13: =D13+E13 | G13: =SUMIFS(Expenses!$D$5:$D$304,Expenses!$A$5:$A$304,">="&$B13,Expenses!$A$5:$A$304,"<="&$C13) | H13: =F13-G13 | I13: =IFERROR(H13/F13,"")
A14: 46296 | B14: 46296 | C14: =EOMONTH(B14,0) | D14: =SUMIFS(Income!$D$5:$D$154,Income!$A$5:$A$154,">="&$B14,Income!$A$5:$A$154,"<="&$C14,Income!$B$5:$B$154,'Start Here'!$C$6) | E14: =SUMIFS(Income!$D$5:$D$154,Income!$A$5:$A$154,">="&$B14,Income!$A$5:$A$154,"<="&$C14,Income!$B$5:$B$154,'Start Here'!$C$7) | F14: =D14+E14 | G14: =SUMIFS(Expenses!$D$5:$D$304,Expenses!$A$5:$A$304,">="&$B14,Expenses!$A$5:$A$304,"<="&$C14) | H14: =F14-G14 | I14: =IFERROR(H14/F14,"")
A15: 46327 | B15: 46327 | C15: =EOMONTH(B15,0) | D15: =SUMIFS(Income!$D$5:$D$154,Income!$A$5:$A$154,">="&$B15,Income!$A$5:$A$154,"<="&$C15,Income!$B$5:$B$154,'Start Here'!$C$6) | E15: =SUMIFS(Income!$D$5:$D$154,Income!$A$5:$A$154,">="&$B15,Income!$A$5:$A$154,"<="&$C15,Income!$B$5:$B$154,'Start Here'!$C$7) | F15: =D15+E15 | G15: =SUMIFS(Expenses!$D$5:$D$304,Expenses!$A$5:$A$304,">="&$B15,Expenses!$A$5:$A$304,"<="&$C15) | H15: =F15-G15 | I15: =IFERROR(H15/F15,"")
A16: 46357 | B16: 46357 | C16: =EOMONTH(B16,0) | D16: =SUMIFS(Income!$D$5:$D$154,Income!$A$5:$A$154,">="&$B16,Income!$A$5:$A$154,"<="&$C16,Income!$B$5:$B$154,'Start Here'!$C$6) | E16: =SUMIFS(Income!$D$5:$D$154,Income!$A$5:$A$154,">="&$B16,Income!$A$5:$A$154,"<="&$C16,Income!$B$5:$B$154,'Start Here'!$C$7) | F16: =D16+E16 | G16: =SUMIFS(Expenses!$D$5:$D$304,Expenses!$A$5:$A$304,">="&$B16,Expenses!$A$5:$A$304,"<="&$C16) | H16: =F16-G16 | I16: =IFERROR(H16/F16,"")
A17: YEAR TOTAL | D17: =SUM(D5:D16) | E17: =SUM(E5:E16) | F17: =SUM(F5:F16) | G17: =SUM(G5:G16) | H17: =F17-G17 | I17: =IFERROR(H17/F17,"")
A18: MONTHLY AVERAGE | D18: =IFERROR(AVERAGEIF($F$5:$F$16,"<>0",D$5:D$16),0) | E18: =IFERROR(AVERAGEIF($F$5:$F$16,"<>0",E$5:E$16),0) | F18: =IFERROR(AVERAGEIF($F$5:$F$16,"<>0",F$5:F$16),0) | G18: =IFERROR(AVERAGEIF($F$5:$F$16,"<>0",G$5:G$16),0) | H18: =IFERROR(AVERAGEIF($F$5:$F$16,"<>0",H$5:H$16),0) | I18: =IFERROR(H18/F18,"") | K18: Average across months that had income logged, so empty future months don't drag it down.
A21: SPENDING BY CATEGORY
A22: Category | B22: =B5 | C22: =B6 | D22: =B7 | E22: =B8 | F22: =B9 | G22: =B10 | H22: =B11 | I22: =B12 | J22: =B13 | K22: =B14 | L22: =B15 | M22: =B16 | N22: Year Total | O22: % of Spend
A23: ='Start Here'!$C$10 | B23: =SUMIFS(Expenses!$D$5:$D$304,Expenses!$A$5:$A$304,">="&B$22,Expenses!$A$5:$A$304,"<="&EOMONTH(B$22,0),Expenses!$B$5:$B$304,$A23) | C23: =SUMIFS(Expenses!$D$5:$D$304,Expenses!$A$5:$A$304,">="&C$22,Expenses!$A$5:$A$304,"<="&EOMONTH(C$22,0),Expenses!$B$5:$B$304,$A23) | D23: =SUMIFS(Expenses!$D$5:$D$304,Expenses!$A$5:$A$304,">="&D$22,Expenses!$A$5:$A$304,"<="&EOMONTH(D$22,0),Expenses!$B$5:$B$304,$A23) | E23: =SUMIFS(Expenses!$D$5:$D$304,Expenses!$A$5:$A$304,">="&E$22,Expenses!$A$5:$A$304,"<="&EOMONTH(E$22,0),Expenses!$B$5:$B$304,$A23) | F23: =SUMIFS(Expenses!$D$5:$D$304,Expenses!$A$5:$A$304,">="&F$22,Expenses!$A$5:$A$304,"<="&EOMONTH(F$22,0),Expenses!$B$5:$B$304,$A23) | G23: =SUMIFS(Expenses!$D$5:$D$304,Expenses!$A$5:$A$304,">="&G$22,Expenses!$A$5:$A$304,"<="&EOMONTH(G$22,0),Expenses!$B$5:$B$304,$A23) | H23: =SUMIFS(Expenses!$D$5:$D$304,Expenses!$A$5:$A$304,">="&H$22,Expenses!$A$5:$A$304,"<="&EOMONTH(H$22,0),Expenses!$B$5:$B$304,$A23) | I23: =SUMIFS(Expenses!$D$5:$D$304,Expenses!$A$5:$A$304,">="&I$22,Expenses!$A$5:$A$304,"<="&EOMONTH(I$22,0),Expenses!$B$5:$B$304,$A23) | ... M23: =SUMIFS(Expenses!$D$5:$D$304,Expenses!$A$5:$A$304,">="&M$22,Expenses!$A$5:$A$304,"<="&EOMONTH(M$22,0),Expenses!$B$5:$B$304,$A23) | N23: =SUM(B23:M23) | O23: =IFERROR($N23/$N$37,"")
A24: ='Start Here'!$C$11 | B24: =SUMIFS(Expenses!$D$5:$D$304,Expenses!$A$5:$A$304,">="&B$22,Expenses!$A$5:$A$304,"<="&EOMONTH(B$22,0),Expenses!$B$5:$B$304,$A24) | C24: =SUMIFS(Expenses!$D$5:$D$304,Expenses!$A$5:$A$304,">="&C$22,Expenses!$A$5:$A$304,"<="&EOMONTH(C$22,0),Expenses!$B$5:$B$304,$A24) | D24: =SUMIFS(Expenses!$D$5:$D$304,Expenses!$A$5:$A$304,">="&D$22,Expenses!$A$5:$A$304,"<="&EOMONTH(D$22,0),Expenses!$B$5:$B$304,$A24) | E24: =SUMIFS(Expenses!$D$5:$D$304,Expenses!$A$5:$A$304,">="&E$22,Expenses!$A$5:$A$304,"<="&EOMONTH(E$22,0),Expenses!$B$5:$B$304,$A24) | F24: =SUMIFS(Expenses!$D$5:$D$304,Expenses!$A$5:$A$304,">="&F$22,Expenses!$A$5:$A$304,"<="&EOMONTH(F$22,0),Expenses!$B$5:$B$304,$A24) | G24: =SUMIFS(Expenses!$D$5:$D$304,Expenses!$A$5:$A$304,">="&G$22,Expenses!$A$5:$A$304,"<="&EOMONTH(G$22,0),Expenses!$B$5:$B$304,$A24) | H24: =SUMIFS(Expenses!$D$5:$D$304,Expenses!$A$5:$A$304,">="&H$22,Expenses!$A$5:$A$304,"<="&EOMONTH(H$22,0),Expenses!$B$5:$B$304,$A24) | I24: =SUMIFS(Expenses!$D$5:$D$304,Expenses!$A$5:$A$304,">="&I$22,Expenses!$A$5:$A$304,"<="&EOMONTH(I$22,0),Expenses!$B$5:$B$304,$A24) | ... M24: =SUMIFS(Expenses!$D$5:$D$304,Expenses!$A$5:$A$304,">="&M$22,Expenses!$A$5:$A$304,"<="&EOMONTH(M$22,0),Expenses!$B$5:$B$304,$A24) | N24: =SUM(B24:M24) | O24: =IFERROR($N24/$N$37,"")
A25: ='Start Here'!$C$12 | B25: =SUMIFS(Expenses!$D$5:$D$304,Expenses!$A$5:$A$304,">="&B$22,Expenses!$A$5:$A$304,"<="&EOMONTH(B$22,0),Expenses!$B$5:$B$304,$A25) | C25: =SUMIFS(Expenses!$D$5:$D$304,Expenses!$A$5:$A$304,">="&C$22,Expenses!$A$5:$A$304,"<="&EOMONTH(C$22,0),Expenses!$B$5:$B$304,$A25) | D25: =SUMIFS(Expenses!$D$5:$D$304,Expenses!$A$5:$A$304,">="&D$22,Expenses!$A$5:$A$304,"<="&EOMONTH(D$22,0),Expenses!$B$5:$B$304,$A25) | E25: =SUMIFS(Expenses!$D$5:$D$304,Expenses!$A$5:$A$304,">="&E$22,Expenses!$A$5:$A$304,"<="&EOMONTH(E$22,0),Expenses!$B$5:$B$304,$A25) | F25: =SUMIFS(Expenses!$D$5:$D$304,Expenses!$A$5:$A$304,">="&F$22,Expenses!$A$5:$A$304,"<="&EOMONTH(F$22,0),Expenses!$B$5:$B$304,$A25) | G25: =SUMIFS(Expenses!$D$5:$D$304,Expenses!$A$5:$A$304,">="&G$22,Expenses!$A$5:$A$304,"<="&EOMONTH(G$22,0),Expenses!$B$5:$B$304,$A25) | H25: =SUMIFS(Expenses!$D$5:$D$304,Expenses!$A$5:$A$304,">="&H$22,Expenses!$A$5:$A$304,"<="&EOMONTH(H$22,0),Expenses!$B$5:$B$304,$A25) | I25: =SUMIFS(Expenses!$D$5:$D$304,Expenses!$A$5:$A$304,">="&I$22,Expenses!$A$5:$A$304,"<="&EOMONTH(I$22,0),Expenses!$B$5:$B$304,$A25) | ... M25: =SUMIFS(Expenses!$D$5:$D$304,Expenses!$A$5:$A$304,">="&M$22,Expenses!$A$5:$A$304,"<="&EOMONTH(M$22,0),Expenses!$B$5:$B$304,$A25) | N25: =SUM(B25:M25) | O25: =IFERROR($N25/$N$37,"")
A26: ='Start Here'!$C$13 | B26: =SUMIFS(Expenses!$D$5:$D$304,Expenses!$A$5:$A$304,">="&B$22,Expenses!$A$5:$A$304,"<="&EOMONTH(B$22,0),Expenses!$B$5:$B$304,$A26) | C26: =SUMIFS(Expenses!$D$5:$D$304,Expenses!$A$5:$A$304,">="&C$22,Expenses!$A$5:$A$304,"<="&EOMONTH(C$22,0),Expenses!$B$5:$B$304,$A26) | D26: =SUMIFS(Expenses!$D$5:$D$304,Expenses!$A$5:$A$304,">="&D$22,Expenses!$A$5:$A$304,"<="&EOMONTH(D$22,0),Expenses!$B$5:$B$304,$A26) | E26: =SUMIFS(Expenses!$D$5:$D$304,Expenses!$A$5:$A$304,">="&E$22,Expenses!$A$5:$A$304,"<="&EOMONTH(E$22,0),Expenses!$B$5:$B$304,$A26) | F26: =SUMIFS(Expenses!$D$5:$D$304,Expenses!$A$5:$A$304,">="&F$22,Expenses!$A$5:$A$304,"<="&EOMONTH(F$22,0),Expenses!$B$5:$B$304,$A26) | G26: =SUMIFS(Expenses!$D$5:$D$304,Expenses!$A$5:$A$304,">="&G$22,Expenses!$A$5:$A$304,"<="&EOMONTH(G$22,0),Expenses!$B$5:$B$304,$A26) | H26: =SUMIFS(Expenses!$D$5:$D$304,Expenses!$A$5:$A$304,">="&H$22,Expenses!$A$5:$A$304,"<="&EOMONTH(H$22,0),Expenses!$B$5:$B$304,$A26) | I26: =SUMIFS(Expenses!$D$5:$D$304,Expenses!$A$5:$A$304,">="&I$22,Expenses!$A$5:$A$304,"<="&EOMONTH(I$22,0),Expenses!$B$5:$B$304,$A26) | ... M26: =SUMIFS(Expenses!$D$5:$D$304,Expenses!$A$5:$A$304,">="&M$22,Expenses!$A$5:$A$304,"<="&EOMONTH(M$22,0),Expenses!$B$5:$B$304,$A26) | N26: =SUM(B26:M26) | O26: =IFERROR($N26/$N$37,"")
A27: ='Start Here'!$C$14 | B27: =SUMIFS(Expenses!$D$5:$D$304,Expenses!$A$5:$A$304,">="&B$22,Expenses!$A$5:$A$304,"<="&EOMONTH(B$22,0),Expenses!$B$5:$B$304,$A27) | C27: =SUMIFS(Expenses!$D$5:$D$304,Expenses!$A$5:$A$304,">="&C$22,Expenses!$A$5:$A$304,"<="&EOMONTH(C$22,0),Expenses!$B$5:$B$304,$A27) | D27: =SUMIFS(Expenses!$D$5:$D$304,Expenses!$A$5:$A$304,">="&D$22,Expenses!$A$5:$A$304,"<="&EOMONTH(D$22,0),Expenses!$B$5:$B$304,$A27) | E27: =SUMIFS(Expenses!$D$5:$D$304,Expenses!$A$5:$A$304,">="&E$22,Expenses!$A$5:$A$304,"<="&EOMONTH(E$22,0),Expenses!$B$5:$B$304,$A27) | F27: =SUMIFS(Expenses!$D$5:$D$304,Expenses!$A$5:$A$304,">="&F$22,Expenses!$A$5:$A$304,"<="&EOMONTH(F$22,0),Expenses!$B$5:$B$304,$A27) | G27: =SUMIFS(Expenses!$D$5:$D$304,Expenses!$A$5:$A$304,">="&G$22,Expenses!$A$5:$A$304,"<="&EOMONTH(G$22,0),Expenses!$B$5:$B$304,$A27) | H27: =SUMIFS(Expenses!$D$5:$D$304,Expenses!$A$5:$A$304,">="&H$22,Expenses!$A$5:$A$304,"<="&EOMONTH(H$22,0),Expenses!$B$5:$B$304,$A27) | I27: =SUMIFS(Expenses!$D$5:$D$304,Expenses!$A$5:$A$304,">="&I$22,Expenses!$A$5:$A$304,"<="&EOMONTH(I$22,0),Expenses!$B$5:$B$304,$A27) | ... M27: =SUMIFS(Expenses!$D$5:$D$304,Expenses!$A$5:$A$304,">="&M$22,Expenses!$A$5:$A$304,"<="&EOMONTH(M$22,0),Expenses!$B$5:$B$304,$A27) | N27: =SUM(B27:M27) | O27: =IFERROR($N27/$N$37,"")
A28: ='Start Here'!$C$15 | B28: =SUMIFS(Expenses!$D$5:$D$304,Expenses!$A$5:$A$304,">="&B$22,Expenses!$A$5:$A$304,"<="&EOMONTH(B$22,0),Expenses!$B$5:$B$304,$A28) | C28: =SUMIFS(Expenses!$D$5:$D$304,Expenses!$A$5:$A$304,">="&C$22,Expenses!$A$5:$A$304,"<="&EOMONTH(C$22,0),Expenses!$B$5:$B$304,$A28) | D28: =SUMIFS(Expenses!$D$5:$D$304,Expenses!$A$5:$A$304,">="&D$22,Expenses!$A$5:$A$304,"<="&EOMONTH(D$22,0),Expenses!$B$5:$B$304,$A28) | E28: =SUMIFS(Expenses!$D$5:$D$304,Expenses!$A$5:$A$304,">="&E$22,Expenses!$A$5:$A$304,"<="&EOMONTH(E$22,0),Expenses!$B$5:$B$304,$A28) | F28: =SUMIFS(Expenses!$D$5:$D$304,Expenses!$A$5:$A$304,">="&F$22,Expenses!$A$5:$A$304,"<="&EOMONTH(F$22,0),Expenses!$B$5:$B$304,$A28) | G28: =SUMIFS(Expenses!$D$5:$D$304,Expenses!$A$5:$A$304,">="&G$22,Expenses!$A$5:$A$304,"<="&EOMONTH(G$22,0),Expenses!$B$5:$B$304,$A28) | H28: =SUMIFS(Expenses!$D$5:$D$304,Expenses!$A$5:$A$304,">="&H$22,Expenses!$A$5:$A$304,"<="&EOMONTH(H$22,0),Expenses!$B$5:$B$304,$A28) | I28: =SUMIFS(Expenses!$D$5:$D$304,Expenses!$A$5:$A$304,">="&I$22,Expenses!$A$5:$A$304,"<="&EOMONTH(I$22,0),Expenses!$B$5:$B$304,$A28) | ... M28: =SUMIFS(Expenses!$D$5:$D$304,Expenses!$A$5:$A$304,">="&M$22,Expenses!$A$5:$A$304,"<="&EOMONTH(M$22,0),Expenses!$B$5:$B$304,$A28) | N28: =SUM(B28:M28) | O28: =IFERROR($N28/$N$37,"")
A29: ='Start Here'!$C$16 | B29: =SUMIFS(Expenses!$D$5:$D$304,Expenses!$A$5:$A$304,">="&B$22,Expenses!$A$5:$A$304,"<="&EOMONTH(B$22,0),Expenses!$B$5:$B$304,$A29) | C29: =SUMIFS(Expenses!$D$5:$D$304,Expenses!$A$5:$A$304,">="&C$22,Expenses!$A$5:$A$304,"<="&EOMONTH(C$22,0),Expenses!$B$5:$B$304,$A29) | D29: =SUMIFS(Expenses!$D$5:$D$304,Expenses!$A$5:$A$304,">="&D$22,Expenses!$A$5:$A$304,"<="&EOMONTH(D$22,0),Expenses!$B$5:$B$304,$A29) | E29: =SUMIFS(Expenses!$D$5:$D$304,Expenses!$A$5:$A$304,">="&E$22,Expenses!$A$5:$A$304,"<="&EOMONTH(E$22,0),Expenses!$B$5:$B$304,$A29) | F29: =SUMIFS(Expenses!$D$5:$D$304,Expenses!$A$5:$A$304,">="&F$22,Expenses!$A$5:$A$304,"<="&EOMONTH(F$22,0),Expenses!$B$5:$B$304,$A29) | G29: =SUMIFS(Expenses!$D$5:$D$304,Expenses!$A$5:$A$304,">="&G$22,Expenses!$A$5:$A$304,"<="&EOMONTH(G$22,0),Expenses!$B$5:$B$304,$A29) | H29: =SUMIFS(Expenses!$D$5:$D$304,Expenses!$A$5:$A$304,">="&H$22,Expenses!$A$5:$A$304,"<="&EOMONTH(H$22,0),Expenses!$B$5:$B$304,$A29) | I29: =SUMIFS(Expenses!$D$5:$D$304,Expenses!$A$5:$A$304,">="&I$22,Expenses!$A$5:$A$304,"<="&EOMONTH(I$22,0),Expenses!$B$5:$B$304,$A29) | ... M29: =SUMIFS(Expenses!$D$5:$D$304,Expenses!$A$5:$A$304,">="&M$22,Expenses!$A$5:$A$304,"<="&EOMONTH(M$22,0),Expenses!$B$5:$B$304,$A29) | N29: =SUM(B29:M29) | O29: =IFERROR($N29/$N$37,"")
A30: ='Start Here'!$C$17 | B30: =SUMIFS(Expenses!$D$5:$D$304,Expenses!$A$5:$A$304,">="&B$22,Expenses!$A$5:$A$304,"<="&EOMONTH(B$22,0),Expenses!$B$5:$B$304,$A30) | C30: =SUMIFS(Expenses!$D$5:$D$304,Expenses!$A$5:$A$304,">="&C$22,Expenses!$A$5:$A$304,"<="&EOMONTH(C$22,0),Expenses!$B$5:$B$304,$A30) | D30: =SUMIFS(Expenses!$D$5:$D$304,Expenses!$A$5:$A$304,">="&D$22,Expenses!$A$5:$A$304,"<="&EOMONTH(D$22,0),Expenses!$B$5:$B$304,$A30) | E30: =SUMIFS(Expenses!$D$5:$D$304,Expenses!$A$5:$A$304,">="&E$22,Expenses!$A$5:$A$304,"<="&EOMONTH(E$22,0),Expenses!$B$5:$B$304,$A30) | F30: =SUMIFS(Expenses!$D$5:$D$304,Expenses!$A$5:$A$304,">="&F$22,Expenses!$A$5:$A$304,"<="&EOMONTH(F$22,0),Expenses!$B$5:$B$304,$A30) | G30: =SUMIFS(Expenses!$D$5:$D$304,Expenses!$A$5:$A$304,">="&G$22,Expenses!$A$5:$A$304,"<="&EOMONTH(G$22,0),Expenses!$B$5:$B$304,$A30) | H30: =SUMIFS(Expenses!$D$5:$D$304,Expenses!$A$5:$A$304,">="&H$22,Expenses!$A$5:$A$304,"<="&EOMONTH(H$22,0),Expenses!$B$5:$B$304,$A30) | I30: =SUMIFS(Expenses!$D$5:$D$304,Expenses!$A$5:$A$304,">="&I$22,Expenses!$A$5:$A$304,"<="&EOMONTH(I$22,0),Expenses!$B$5:$B$304,$A30) | ... M30: =SUMIFS(Expenses!$D$5:$D$304,Expenses!$A$5:$A$304,">="&M$22,Expenses!$A$5:$A$304,"<="&EOMONTH(M$22,0),Expenses!$B$5:$B$304,$A30) | N30: =SUM(B30:M30) | O30: =IFERROR($N30/$N$37,"")
A31: ='Start Here'!$C$18 | B31: =SUMIFS(Expenses!$D$5:$D$304,Expenses!$A$5:$A$304,">="&B$22,Expenses!$A$5:$A$304,"<="&EOMONTH(B$22,0),Expenses!$B$5:$B$304,$A31) | C31: =SUMIFS(Expenses!$D$5:$D$304,Expenses!$A$5:$A$304,">="&C$22,Expenses!$A$5:$A$304,"<="&EOMONTH(C$22,0),Expenses!$B$5:$B$304,$A31) | D31: =SUMIFS(Expenses!$D$5:$D$304,Expenses!$A$5:$A$304,">="&D$22,Expenses!$A$5:$A$304,"<="&EOMONTH(D$22,0),Expenses!$B$5:$B$304,$A31) | E31: =SUMIFS(Expenses!$D$5:$D$304,Expenses!$A$5:$A$304,">="&E$22,Expenses!$A$5:$A$304,"<="&EOMONTH(E$22,0),Expenses!$B$5:$B$304,$A31) | F31: =SUMIFS(Expenses!$D$5:$D$304,Expenses!$A$5:$A$304,">="&F$22,Expenses!$A$5:$A$304,"<="&EOMONTH(F$22,0),Expenses!$B$5:$B$304,$A31) | G31: =SUMIFS(Expenses!$D$5:$D$304,Expenses!$A$5:$A$304,">="&G$22,Expenses!$A$5:$A$304,"<="&EOMONTH(G$22,0),Expenses!$B$5:$B$304,$A31) | H31: =SUMIFS(Expenses!$D$5:$D$304,Expenses!$A$5:$A$304,">="&H$22,Expenses!$A$5:$A$304,"<="&EOMONTH(H$22,0),Expenses!$B$5:$B$304,$A31) | I31: =SUMIFS(Expenses!$D$5:$D$304,Expenses!$A$5:$A$304,">="&I$22,Expenses!$A$5:$A$304,"<="&EOMONTH(I$22,0),Expenses!$B$5:$B$304,$A31) | ... M31: =SUMIFS(Expenses!$D$5:$D$304,Expenses!$A$5:$A$304,">="&M$22,Expenses!$A$5:$A$304,"<="&EOMONTH(M$22,0),Expenses!$B$5:$B$304,$A31) | N31: =SUM(B31:M31) | O31: =IFERROR($N31/$N$37,"")
A32: ='Start Here'!$C$19 | B32: =SUMIFS(Expenses!$D$5:$D$304,Expenses!$A$5:$A$304,">="&B$22,Expenses!$A$5:$A$304,"<="&EOMONTH(B$22,0),Expenses!$B$5:$B$304,$A32) | C32: =SUMIFS(Expenses!$D$5:$D$304,Expenses!$A$5:$A$304,">="&C$22,Expenses!$A$5:$A$304,"<="&EOMONTH(C$22,0),Expenses!$B$5:$B$304,$A32) | D32: =SUMIFS(Expenses!$D$5:$D$304,Expenses!$A$5:$A$304,">="&D$22,Expenses!$A$5:$A$304,"<="&EOMONTH(D$22,0),Expenses!$B$5:$B$304,$A32) | E32: =SUMIFS(Expenses!$D$5:$D$304,Expenses!$A$5:$A$304,">="&E$22,Expenses!$A$5:$A$304,"<="&EOMONTH(E$22,0),Expenses!$B$5:$B$304,$A32) | F32: =SUMIFS(Expenses!$D$5:$D$304,Expenses!$A$5:$A$304,">="&F$22,Expenses!$A$5:$A$304,"<="&EOMONTH(F$22,0),Expenses!$B$5:$B$304,$A32) | G32: =SUMIFS(Expenses!$D$5:$D$304,Expenses!$A$5:$A$304,">="&G$22,Expenses!$A$5:$A$304,"<="&EOMONTH(G$22,0),Expenses!$B$5:$B$304,$A32) | H32: =SUMIFS(Expenses!$D$5:$D$304,Expenses!$A$5:$A$304,">="&H$22,Expenses!$A$5:$A$304,"<="&EOMONTH(H$22,0),Expenses!$B$5:$B$304,$A32) | I32: =SUMIFS(Expenses!$D$5:$D$304,Expenses!$A$5:$A$304,">="&I$22,Expenses!$A$5:$A$304,"<="&EOMONTH(I$22,0),Expenses!$B$5:$B$304,$A32) | ... M32: =SUMIFS(Expenses!$D$5:$D$304,Expenses!$A$5:$A$304,">="&M$22,Expenses!$A$5:$A$304,"<="&EOMONTH(M$22,0),Expenses!$B$5:$B$304,$A32) | N32: =SUM(B32:M32) | O32: =IFERROR($N32/$N$37,"")
A33: ='Start Here'!$C$20 | B33: =SUMIFS(Expenses!$D$5:$D$304,Expenses!$A$5:$A$304,">="&B$22,Expenses!$A$5:$A$304,"<="&EOMONTH(B$22,0),Expenses!$B$5:$B$304,$A33) | C33: =SUMIFS(Expenses!$D$5:$D$304,Expenses!$A$5:$A$304,">="&C$22,Expenses!$A$5:$A$304,"<="&EOMONTH(C$22,0),Expenses!$B$5:$B$304,$A33) | D33: =SUMIFS(Expenses!$D$5:$D$304,Expenses!$A$5:$A$304,">="&D$22,Expenses!$A$5:$A$304,"<="&EOMONTH(D$22,0),Expenses!$B$5:$B$304,$A33) | E33: =SUMIFS(Expenses!$D$5:$D$304,Expenses!$A$5:$A$304,">="&E$22,Expenses!$A$5:$A$304,"<="&EOMONTH(E$22,0),Expenses!$B$5:$B$304,$A33) | F33: =SUMIFS(Expenses!$D$5:$D$304,Expenses!$A$5:$A$304,">="&F$22,Expenses!$A$5:$A$304,"<="&EOMONTH(F$22,0),Expenses!$B$5:$B$304,$A33) | G33: =SUMIFS(Expenses!$D$5:$D$304,Expenses!$A$5:$A$304,">="&G$22,Expenses!$A$5:$A$304,"<="&EOMONTH(G$22,0),Expenses!$B$5:$B$304,$A33) | H33: =SUMIFS(Expenses!$D$5:$D$304,Expenses!$A$5:$A$304,">="&H$22,Expenses!$A$5:$A$304,"<="&EOMONTH(H$22,0),Expenses!$B$5:$B$304,$A33) | I33: =SUMIFS(Expenses!$D$5:$D$304,Expenses!$A$5:$A$304,">="&I$22,Expenses!$A$5:$A$304,"<="&EOMONTH(I$22,0),Expenses!$B$5:$B$304,$A33) | ... M33: =SUMIFS(Expenses!$D$5:$D$304,Expenses!$A$5:$A$304,">="&M$22,Expenses!$A$5:$A$304,"<="&EOMONTH(M$22,0),Expenses!$B$5:$B$304,$A33) | N33: =SUM(B33:M33) | O33: =IFERROR($N33/$N$37,"")
A34: ='Start Here'!$C$21 | B34: =SUMIFS(Expenses!$D$5:$D$304,Expenses!$A$5:$A$304,">="&B$22,Expenses!$A$5:$A$304,"<="&EOMONTH(B$22,0),Expenses!$B$5:$B$304,$A34) | C34: =SUMIFS(Expenses!$D$5:$D$304,Expenses!$A$5:$A$304,">="&C$22,Expenses!$A$5:$A$304,"<="&EOMONTH(C$22,0),Expenses!$B$5:$B$304,$A34) | D34: =SUMIFS(Expenses!$D$5:$D$304,Expenses!$A$5:$A$304,">="&D$22,Expenses!$A$5:$A$304,"<="&EOMONTH(D$22,0),Expenses!$B$5:$B$304,$A34) | E34: =SUMIFS(Expenses!$D$5:$D$304,Expenses!$A$5:$A$304,">="&E$22,Expenses!$A$5:$A$304,"<="&EOMONTH(E$22,0),Expenses!$B$5:$B$304,$A34) | F34: =SUMIFS(Expenses!$D$5:$D$304,Expenses!$A$5:$A$304,">="&F$22,Expenses!$A$5:$A$304,"<="&EOMONTH(F$22,0),Expenses!$B$5:$B$304,$A34) | G34: =SUMIFS(Expenses!$D$5:$D$304,Expenses!$A$5:$A$304,">="&G$22,Expenses!$A$5:$A$304,"<="&EOMONTH(G$22,0),Expenses!$B$5:$B$304,$A34) | H34: =SUMIFS(Expenses!$D$5:$D$304,Expenses!$A$5:$A$304,">="&H$22,Expenses!$A$5:$A$304,"<="&EOMONTH(H$22,0),Expenses!$B$5:$B$304,$A34) | I34: =SUMIFS(Expenses!$D$5:$D$304,Expenses!$A$5:$A$304,">="&I$22,Expenses!$A$5:$A$304,"<="&EOMONTH(I$22,0),Expenses!$B$5:$B$304,$A34) | ... M34: =SUMIFS(Expenses!$D$5:$D$304,Expenses!$A$5:$A$304,">="&M$22,Expenses!$A$5:$A$304,"<="&EOMONTH(M$22,0),Expenses!$B$5:$B$304,$A34) | N34: =SUM(B34:M34) | O34: =IFERROR($N34/$N$37,"")
A35: ='Start Here'!$C$22 | B35: =SUMIFS(Expenses!$D$5:$D$304,Expenses!$A$5:$A$304,">="&B$22,Expenses!$A$5:$A$304,"<="&EOMONTH(B$22,0),Expenses!$B$5:$B$304,$A35) | C35: =SUMIFS(Expenses!$D$5:$D$304,Expenses!$A$5:$A$304,">="&C$22,Expenses!$A$5:$A$304,"<="&EOMONTH(C$22,0),Expenses!$B$5:$B$304,$A35) | D35: =SUMIFS(Expenses!$D$5:$D$304,Expenses!$A$5:$A$304,">="&D$22,Expenses!$A$5:$A$304,"<="&EOMONTH(D$22,0),Expenses!$B$5:$B$304,$A35) | E35: =SUMIFS(Expenses!$D$5:$D$304,Expenses!$A$5:$A$304,">="&E$22,Expenses!$A$5:$A$304,"<="&EOMONTH(E$22,0),Expenses!$B$5:$B$304,$A35) | F35: =SUMIFS(Expenses!$D$5:$D$304,Expenses!$A$5:$A$304,">="&F$22,Expenses!$A$5:$A$304,"<="&EOMONTH(F$22,0),Expenses!$B$5:$B$304,$A35) | G35: =SUMIFS(Expenses!$D$5:$D$304,Expenses!$A$5:$A$304,">="&G$22,Expenses!$A$5:$A$304,"<="&EOMONTH(G$22,0),Expenses!$B$5:$B$304,$A35) | H35: =SUMIFS(Expenses!$D$5:$D$304,Expenses!$A$5:$A$304,">="&H$22,Expenses!$A$5:$A$304,"<="&EOMONTH(H$22,0),Expenses!$B$5:$B$304,$A35) | I35: =SUMIFS(Expenses!$D$5:$D$304,Expenses!$A$5:$A$304,">="&I$22,Expenses!$A$5:$A$304,"<="&EOMONTH(I$22,0),Expenses!$B$5:$B$304,$A35) | ... M35: =SUMIFS(Expenses!$D$5:$D$304,Expenses!$A$5:$A$304,">="&M$22,Expenses!$A$5:$A$304,"<="&EOMONTH(M$22,0),Expenses!$B$5:$B$304,$A35) | N35: =SUM(B35:M35) | O35: =IFERROR($N35/$N$37,"")
A36: ='Start Here'!$C$23 | B36: =SUMIFS(Expenses!$D$5:$D$304,Expenses!$A$5:$A$304,">="&B$22,Expenses!$A$5:$A$304,"<="&EOMONTH(B$22,0),Expenses!$B$5:$B$304,$A36) | C36: =SUMIFS(Expenses!$D$5:$D$304,Expenses!$A$5:$A$304,">="&C$22,Expenses!$A$5:$A$304,"<="&EOMONTH(C$22,0),Expenses!$B$5:$B$304,$A36) | D36: =SUMIFS(Expenses!$D$5:$D$304,Expenses!$A$5:$A$304,">="&D$22,Expenses!$A$5:$A$304,"<="&EOMONTH(D$22,0),Expenses!$B$5:$B$304,$A36) | E36: =SUMIFS(Expenses!$D$5:$D$304,Expenses!$A$5:$A$304,">="&E$22,Expenses!$A$5:$A$304,"<="&EOMONTH(E$22,0),Expenses!$B$5:$B$304,$A36) | F36: =SUMIFS(Expenses!$D$5:$D$304,Expenses!$A$5:$A$304,">="&F$22,Expenses!$A$5:$A$304,"<="&EOMONTH(F$22,0),Expenses!$B$5:$B$304,$A36) | G36: =SUMIFS(Expenses!$D$5:$D$304,Expenses!$A$5:$A$304,">="&G$22,Expenses!$A$5:$A$304,"<="&EOMONTH(G$22,0),Expenses!$B$5:$B$304,$A36) | H36: =SUMIFS(Expenses!$D$5:$D$304,Expenses!$A$5:$A$304,">="&H$22,Expenses!$A$5:$A$304,"<="&EOMONTH(H$22,0),Expenses!$B$5:$B$304,$A36) | I36: =SUMIFS(Expenses!$D$5:$D$304,Expenses!$A$5:$A$304,">="&I$22,Expenses!$A$5:$A$304,"<="&EOMONTH(I$22,0),Expenses!$B$5:$B$304,$A36) | ... M36: =SUMIFS(Expenses!$D$5:$D$304,Expenses!$A$5:$A$304,">="&M$22,Expenses!$A$5:$A$304,"<="&EOMONTH(M$22,0),Expenses!$B$5:$B$304,$A36) | N36: =SUM(B36:M36) | O36: =IFERROR($N36/$N$37,"")
A37: TOTAL | B37: =SUM(B23:B36) | C37: =SUM(C23:C36) | D37: =SUM(D23:D36) | E37: =SUM(E23:E36) | F37: =SUM(F23:F36) | G37: =SUM(G23:G36) | H37: =SUM(H23:H36) | I37: =SUM(I23:I36) | ... N37: =SUM(N23:N36) | O37: =IFERROR(N37/N37,"")
A39: Category totals only count expenses whose category matches a label on the Start Here tab — if a row on the Expenses tab is left uncategorised it lands in the monthly totals above but not in this grid.
